vexy_glob-1.0.9.dist-info/METADATA
vexy_glob-1.0.9.dist-info/WHEEL
vexy_glob-1.0.9.dist-info/entry_points.txt
vexy_glob-1.0.9.dist-info/licenses/LICENSE
vexy_glob/__init__.py
vexy_glob/__main__.py
vexy_glob/_vexy_glob.abi3.so
vexy_glob-1.0.9.dist-info/RECORD
