Metadata-Version: 2.4
Name: vexy-glob
Version: 1.0.9
Classifier: Development Status :: 3 - Alpha
Classifier: Intended Audience :: Developers
Classifier: License :: OSI Approved :: MIT License
Classifier: Operating System :: OS Independent
Classifier: Programming Language :: Python :: 3
Classifier: Programming Language :: Python :: 3.8
Classifier: Programming Language :: Python :: 3.9
Classifier: Programming Language :: Python :: 3.10
Classifier: Programming Language :: Python :: 3.11
Classifier: Programming Language :: Python :: 3.12
Classifier: Programming Language :: Rust
Classifier: Topic :: Software Development :: Libraries
Classifier: Topic :: System :: Filesystems
Requires-Dist: fire>=0.7.0
Requires-Dist: rich>=14.1.0
License-File: LICENSE
Summary: Vexy Glob fast file finding
Keywords: filesystem,find,glob,parallel,rust,search
Author-email: Adam Twardoch <adam+github@twardoch.com>
License: MIT
Requires-Python: >=3.8
Project-URL: Bug Tracker, https://github.com/vexyart/vexy-glob/issues
Project-URL: Homepage, https://github.com/vexyart/vexy-glob
Project-URL: Repository, https://github.com/vexyart/vexy-glob
